napari_rembg/__init__.py
napari_rembg/_base_segmentation_widget.py
napari_rembg/_rembg.py
napari_rembg/local_predictor_widget.py
napari_rembg/napari.yaml
napari_rembg/remote_predictor_widget.py
napari_rembg/segmentation_api_client.py
napari_rembg/_tests/__init__.py
napari_rembg/_tests/test_widget.py
napari_rembg-0.0.7.dist-info/LICENSE
napari_rembg-0.0.7.dist-info/METADATA
napari_rembg-0.0.7.dist-info/WHEEL
napari_rembg-0.0.7.dist-info/entry_points.txt
napari_rembg-0.0.7.dist-info/top_level.txt
napari_rembg-0.0.7.dist-info/RECORD
