Metadata-Version: 2.1
Name: napari-rembg
Version: 0.0.7
Summary: AI-based foreground extraction in scientific and natural images.
Home-page: https://github.com/EPFL-Center-for-Imaging/napari-rembg.git
Author: Mallory Wittwer
Author-email: mallory.wittwer@epfl.ch
License: BSD-3-Clause
Project-URL: Source Code, https://github.com/EPFL-Center-for-Imaging/napari-rembg.git
Classifier: Development Status :: 2 - Pre-Alpha
Classifier: Framework :: napari
Classifier: Intended Audience :: Developers
Classifier: License :: OSI Approved :: BSD License
Classifier: Operating System :: OS Independent
Classifier: Programming Language :: Python
Classifier: Programming Language :: Python :: 3
Classifier: Programming Language :: Python :: 3 :: Only
Classifier: Programming Language :: Python :: 3.8
Classifier: Programming Language :: Python :: 3.9
Classifier: Programming Language :: Python :: 3.10
Classifier: Topic :: Scientific/Engineering :: Image Processing
Requires-Python: >=3.8
License-File: LICENSE
Requires-Dist: magicgui
Requires-Dist: qtpy
Requires-Dist: napari[all] >=0.4.16
Provides-Extra: local
Requires-Dist: rembg ; extra == 'local'
Provides-Extra: testing
Requires-Dist: pytest ; extra == 'testing'
Requires-Dist: pytest-cov ; extra == 'testing'
Requires-Dist: pytest-qt ; extra == 'testing'
Requires-Dist: napari ; extra == 'testing'
Requires-Dist: pyqt5 ; extra == 'testing'
